pymigaguide/__init__.py
pymigaguide/app.py
pymigaguide/cli.py
pymigaguide/model.py
pymigaguide/parser.py
pymigaguide/regex.py
pymigaguide/widgets/__init__.py
pymigaguide/widgets/flowtext.py
pymigaguide/widgets/guidetoolbar.py
pymigaguide/widgets/guideview.py
pymigaguide/writer/html.py
pymigaguide/writer/json.py
pymigaguide/writer/markdown.py
pymigaguide/writer/txt.py
pymigaguide-0.0.2.dist-info/entry_points.txt
pymigaguide-0.0.2.dist-info/licenses/LICENSE.md
pymigaguide-0.0.2.dist-info/WHEEL
pymigaguide-0.0.2.dist-info/METADATA
pymigaguide-0.0.2.dist-info/RECORD
