Metadata-Version: 2.4
Name: pymigaguide
Version: 0.0.2
Summary: Amiga .guide viewer
Author-email: Gareth Davidson <gaz@bitplane.net>
Requires-Python: >=3.10
License-File: LICENSE.md
Requires-Dist: pydantic
Requires-Dist: chardet
Requires-Dist: textual
Requires-Dist: pre-commit ; extra == "dev"
Requires-Dist: pytest ; extra == "dev"
Requires-Dist: coverage ; extra == "dev"
Requires-Dist: pytest-cov ; extra == "dev"
Requires-Dist: build ; extra == "dev"
Requires-Dist: twine ; extra == "dev"
Requires-Dist: ruff ; extra == "dev"
Requires-Dist: mkdocs ; extra == "dev"
Requires-Dist: mkdocs-material ; extra == "dev"
Requires-Dist: pydoc-markdown ; extra == "dev"
Requires-Dist: pytest-asyncio ; extra == "dev"
Provides-Extra: dev
